pulse_schemas/__init__.py
pulse_schemas/schema.py
pulse_schemas-0.5.0.dist-info/licenses/LICENSE
pulse_schemas-0.5.0.dist-info/METADATA
pulse_schemas-0.5.0.dist-info/WHEEL
pulse_schemas-0.5.0.dist-info/top_level.txt
pulse_schemas-0.5.0.dist-info/RECORD
