Metadata-Version: 2.4
Name: pulse_schemas
Version: 0.5.0
Summary: A pydantic schema manager
Author-email: Wilson <your.email@example.com>
License: MIT License
Classifier: License :: OSI Approved :: MIT License
Classifier: Programming Language :: Python :: 3
Classifier: Operating System :: OS Independent
Requires-Python: >=3.8
License-File: LICENSE
Dynamic: license-file
